secret_handshake/__init__.py
secret_handshake/boxstream.py
secret_handshake/crypto.py
secret_handshake/network.py
secret_handshake/test_boxstream.py
secret_handshake/test_crypto.py
secret_handshake/util.py
secret_handshake-0.1.0.dev2.dist-info/DESCRIPTION.rst
secret_handshake-0.1.0.dev2.dist-info/METADATA
secret_handshake-0.1.0.dev2.dist-info/RECORD
secret_handshake-0.1.0.dev2.dist-info/WHEEL
secret_handshake-0.1.0.dev2.dist-info/metadata.json
secret_handshake-0.1.0.dev2.dist-info/top_level.txt
