Metadata-Version: 2.0
Name: secret-handshake
Version: 0.1.0.dev2
Summary: A module that implements Secret Handshake as specified in "Designing a Secret Handshake: Authenticated
Requires-Dist: async-generator (==1.8)
Requires-Dist: pynacl (==1.1.2)
Provides-Extra: all
Requires-Dist: Sphinx (>=1.6.2); extra == 'all'
Requires-Dist: check-manifest (>=0.25); extra == 'all'
Requires-Dist: coverage (>=4.0); extra == 'all'
Requires-Dist: isort (>=4.2.2); extra == 'all'
Requires-Dist: pep257 (>=0.7.0); extra == 'all'
Requires-Dist: pytest-cov (>=1.8.0); extra == 'all'
Requires-Dist: pytest (>=3.1.1); extra == 'all'
Requires-Dist: pytest-asyncio (==0.6.0); extra == 'all'
Provides-Extra: docs
Requires-Dist: Sphinx (>=1.6.2); extra == 'docs'
Provides-Extra: tests
Requires-Dist: check-manifest (>=0.25); extra == 'tests'
Requires-Dist: coverage (>=4.0); extra == 'tests'
Requires-Dist: isort (>=4.2.2); extra == 'tests'
Requires-Dist: pep257 (>=0.7.0); extra == 'tests'
Requires-Dist: pytest-cov (>=1.8.0); extra == 'tests'
Requires-Dist: pytest (>=3.1.1); extra == 'tests'
Requires-Dist: pytest-asyncio (==0.6.0); extra == 'tests'
